DungeonGenerator/__init__.py
DungeonGenerator/backgrounds.py
DungeonGenerator/character_builder.py
DungeonGenerator/cr.py
DungeonGenerator/dungeon.py
DungeonGenerator/gear.py
DungeonGenerator/gear_lib.py
DungeonGenerator/monsters.py
DungeonGenerator/monsters_lib.py
DungeonGenerator/npc.py
DungeonGenerator/npc_lib.py
DungeonGenerator/player_lib.py
DungeonGenerator/quest.py
DungeonGenerator/quest_lib.py
DungeonGenerator/room_lib.py
DungeonGenerator/skills.py
DungeonGenerator/spells.py
DungeonGenerator/traps.py
DungeonGenerator/treasure.py
DungeonGenerator/utilities.py
DungeonGenerator-0.2.4.dist-info/METADATA
DungeonGenerator-0.2.4.dist-info/WHEEL
DungeonGenerator-0.2.4.dist-info/top_level.txt
DungeonGenerator-0.2.4.dist-info/RECORD
